stmaterial/__init__.py
stmaterial/_navigation.py
stmaterial/_transforms.py
stmaterial/_translations.py
stmaterial/assets/scripts/gumshoe-patched.js
stmaterial/assets/scripts/materialize.js
stmaterial/assets/scripts/stmaterial.js
stmaterial/assets/styles/base/_index.sass
stmaterial/assets/styles/base/_theme.sass
stmaterial/assets/styles/base/_typography.scss
stmaterial/assets/styles/components/_article-bottom.scss
stmaterial/assets/styles/components/_article-top.scss
stmaterial/assets/styles/components/_back-to-top.scss
stmaterial/assets/styles/components/_brand-logo.scss
stmaterial/assets/styles/components/_breadcrumb.scss
stmaterial/assets/styles/components/_dropdown.scss
stmaterial/assets/styles/components/_index.sass
stmaterial/assets/styles/components/_prev-next.scss
stmaterial/assets/styles/components/_scrollbar.scss
stmaterial/assets/styles/components/_search-button.scss
stmaterial/assets/styles/components/_search-field.sass
stmaterial/assets/styles/components/_search.sass
stmaterial/assets/styles/components/_searchbox.scss
stmaterial/assets/styles/components/_sidenav-icons.scss
stmaterial/assets/styles/components/_sidenav-toggle.scss
stmaterial/assets/styles/components/_table-of-contents.sass
stmaterial/assets/styles/content/_admonitions.sass
stmaterial/assets/styles/content/_api.sass
stmaterial/assets/styles/content/_blocks.sass
stmaterial/assets/styles/content/_code.sass
stmaterial/assets/styles/content/_footnotes.sass
stmaterial/assets/styles/content/_gui-labels.sass
stmaterial/assets/styles/content/_images.sass
stmaterial/assets/styles/content/_index.sass
stmaterial/assets/styles/content/_indexes.sass
stmaterial/assets/styles/content/_lists.sass
stmaterial/assets/styles/content/_math.sass
stmaterial/assets/styles/content/_misc.sass
stmaterial/assets/styles/content/_rubrics.sass
stmaterial/assets/styles/content/_sidebar.sass
stmaterial/assets/styles/content/_spans.scss
stmaterial/assets/styles/content/_tables.sass
stmaterial-0.0.8.dist-info/LICENSE
stmaterial-0.0.8.dist-info/METADATA
stmaterial-0.0.8.dist-info/WHEEL
stmaterial-0.0.8.dist-info/entry_points.txt
stmaterial-0.0.8.dist-info/RECORD