Metadata-Version: 2.1
Name: stmaterial
Version: 0.0.8
Summary: A sphinx theme of materializecss.
Author-Email: zclab <syfhub@hotmail.com>
License: MIT License
Classifier: Development Status :: 2 - Pre-Alpha
Classifier: Framework :: Sphinx
Classifier: Framework :: Sphinx :: Theme
Classifier: License :: OSI Approved :: MIT License
Classifier: Environment :: Web Environment
Classifier: Intended Audience :: Developers
Classifier: Programming Language :: Python :: 3
Classifier: Programming Language :: Python :: 3.8
Classifier: Programming Language :: Python :: 3.9
Classifier: Programming Language :: Python :: 3.10
Classifier: Programming Language :: Python :: 3.11
Classifier: Operating System :: OS Independent
Classifier: Topic :: Documentation
Classifier: Topic :: Software Development :: Documentation
Project-URL: Repository, https://github.com/zclab/stmaterial
Project-URL: Documentation, https://stmaterial.readthedocs.io/en/latest/
Requires-Python: >=3.8
Requires-Dist: beautifulsoup4
Requires-Dist: sphinx<8.0,>=5.0
Requires-Dist: sphinx-basic-ng
Requires-Dist: pygments>=2.7
Requires-Dist: sphinx-theme-builder[cli]>=0.2.0b2; extra == "dev"
Provides-Extra: dev
